nhpylm
