Metadata-Version: 2.4
Name: nhpylm
Version: 0.0.1.1
Summary: Implementation of Nested Hierarchical Pitman-Yor Language Model for Python
Author-email: Vojtech Lanz <vojtech.lanz@gmail.com>, "Jan Hajic jr." <hajicj@ufal.mff.cuni.cz>
Maintainer-email: Vojtech Lanz <vojtech.lanz@gmail.com>
License: Copyright (c) 2022-2025 Vojtech Lanz and others
Project-URL: Homepage, https://github.com/lanzv/nhpylm
Project-URL: Documentation, https://github.com/lanzv/nhpylm
Project-URL: Repository, https://github.com/lanzv/nhpylm.git
Keywords: nhpylm,non-parametric bayessian statistics,segmentation,classification
Classifier: Development Status :: 2 - Pre-Alpha
Classifier: Intended Audience :: Science/Research
Classifier: Topic :: Scientific/Engineering :: Information Analysis
Classifier: License :: OSI Approved :: MIT License
Classifier: Programming Language :: Python
Requires-Python: >=3.10
License-File: LICENSE
Requires-Dist: numpy==2.2.0
Provides-Extra: dev
Requires-Dist: setuptools; extra == "dev"
Requires-Dist: build; extra == "dev"
Requires-Dist: Cython==3.0.12; extra == "dev"
Requires-Dist: numpy<2.0; extra == "dev"
Provides-Extra: examples
Provides-Extra: tests
Dynamic: license-file
